IonDiff/__init__.py
IonDiff/analyze_correlations.py
IonDiff/analyze_descriptors.py
IonDiff/common_library.py
IonDiff/identify_diffusion.py
IonDiff-1.6.dist-info/LICENSE
IonDiff-1.6.dist-info/METADATA
IonDiff-1.6.dist-info/WHEEL
IonDiff-1.6.dist-info/top_level.txt
IonDiff-1.6.dist-info/RECORD
