Metadata-Version: 2.1
Name: IonDiff
Version: 1.6
Summary: Unsupervised identification and analysis of ion-hopping events in solid state electrolytes.
Home-page: https://github.com/IonRepo/IonDiff
Download-URL: https://github.com/IonRepo/IonDiff/archive/refs/tags/0.1.tar.gz
Author: Cibrán López Álvarez
Author-email: cibran.lopez@upc.edu
License: MIT License
Keywords: Ionic Diffusion,Unsupervised Clustering,Machine Learning
Classifier: Development Status :: 3 - Alpha
Classifier: Intended Audience :: Developers
Classifier: Topic :: Software Development :: Build Tools
Classifier: License :: OSI Approved :: MIT License
Classifier: Programming Language :: Python :: 3
License-File: LICENSE
Requires-Dist: numpy
Requires-Dist: scipy
Requires-Dist: scikit-learn
Requires-Dist: multiprocess
Requires-Dist: seaborn
